{
  "heroTitleEn": "A Place to Belong,\nBelieve & Grow",
  "heroTitleTa": "சேர்ந்திருக்க, நம்பிக்கை கொள்ள,\nவளர்ந்திட ஒரு இடம்",
  "heroSubtitleEn": "Join us every Sunday as we worship together, build community, and walk in faith.",
  "heroSubtitleTa": "ஒவ்வொரு ஞாயிற்றுக்கிழமையும் நாம் ஒன்றாக ஆராதித்து, சமுதாயம் கட்டி, விசுவாசத்தில் நடப்போம்.",
  "heroBgImage": "/assets/images/hero-bg.jpg",
  "verseEn": "I have placed before you an open door that no one can shut.",
  "verseTa": "யாரும் மூட முடியாத ஒரு திறந்த வாசலை உனக்கு முன்பாக வைத்திருக்கிறேன்.",
  "verseRefEn": "Revelation 3:8",
  "verseRefTa": "வெளிப்படுத்தல் 3:8",
  "cards": [
    { "icon": "📖", "titleEn": "Word & Worship", "titleTa": "வசனமும் ஆராதனையும்", "descEn": "Spirit-filled messages rooted in scripture every Sunday morning.", "descTa": "ஒவ்வொரு ஞாயிற்றுக்கிழமையும் வேதத்தில் வேரூன்றிய ஆவியானவரின் செய்தி." },
    { "icon": "👥", "titleEn": "Community", "titleTa": "சமுதாயம்", "descEn": "Small groups, fellowships, and events to connect and grow together.", "descTa": "சிறு குழுக்கள், கூட்டுறவு மற்றும் நிகழ்வுகள் மூலம் இணைந்து வளர்வோம்." },
    { "icon": "❤️", "titleEn": "Outreach", "titleTa": "சமூக சேவை", "descEn": "Serving our city and beyond through love and practical action.", "descTa": "அன்பு மற்றும் செயல்வழி நம் நகரத்திற்கும் அப்பாலும் சேவை செய்கிறோம்." },
    { "icon": "⭐", "titleEn": "Children & Youth", "titleTa": "குழந்தைகளும் இளைஞரும்", "descEn": "Safe, fun, and faith-building programmes for all ages.", "descTa": "அனைத்து வயதினருக்கும் விசுவாசம் வளர்க்கும் நிகழ்ச்சிகள்." }
  ]
}
